Metadata-Version: 2.1
Name: AnjaliPython
Version: 0.0.1
Summary: this is a trial package used for calculation.
Home-page: 
Author: Anjali K
Author-email: anjalik7007@gmail.com
License: MIT
Platform: UNKNOWN
License-File: LICENCE.txt
